{
	"map": {
		"width": 6,
		"height": 6,
		"data": [
			0, 1, 2, 3, 4, 5,
			0, 1, 2, 3, 4, 5,
			0, 1, 2, 3, 4, 5,
			0, 1, 2, 3, 4, 5,
			0, 1, 2, 3, 4, 5,
			0, 1, 2, 3, 4, 5
		]
	},
	"textureAtlases": ["assets/cavesofgallet_tiles.png"],
	"blockDescriptions": [
		{"id": 0, "name": "", "atlasIndex": 0, "textureRect": [0, 0, 8, 8]},
		{"id": 1, "name": "", "atlasIndex": 0, "textureRect": [8, 0, 8, 8]},
		{"id": 2, "name": "", "atlasIndex": 0, "textureRect": [16, 0, 8, 8]},
		{"id": 3, "name": "", "atlasIndex": 0, "textureRect": [24, 0, 8, 8]},
		{"id": 4, "name": "", "atlasIndex": 0, "textureRect": [32, 0, 8, 8]},
		{"id": 5, "name": "", "atlasIndex": 0, "textureRect": [40, 0, 8, 8]},
		{"id": 6, "name": "", "atlasIndex": 0, "textureRect": [48, 0, 8, 8]},
		{"id": 7, "name": "", "atlasIndex": 0, "textureRect": [56, 0, 8, 8]},
		{"id": 8, "name": "", "atlasIndex": 0, "textureRect": [0, 8, 8, 8]},
		{"id": 9, "name": "", "atlasIndex": 0, "textureRect": [8, 8, 8, 8]},
		{"id": 10, "name": "", "atlasIndex": 0, "textureRect": [16, 8, 8, 8]},
		{"id": 11, "name": "", "atlasIndex": 0, "textureRect": [24, 8, 8, 8]},
		{"id": 12, "name": "", "atlasIndex": 0, "textureRect": [32, 8, 8, 8]},
		{"id": 13, "name": "", "atlasIndex": 0, "textureRect": [40, 8, 8, 8]},
		{"id": 14, "name": "", "atlasIndex": 0, "textureRect": [48, 8, 8, 8]},
		{"id": 15, "name": "", "atlasIndex": 0, "textureRect": [56, 8, 8, 8]},
		{"id": 16, "name": "", "atlasIndex": 0, "textureRect": [0, 16, 8, 8]},
		{"id": 17, "name": "", "atlasIndex": 0, "textureRect": [8, 16, 8, 8]},
		{"id": 18, "name": "", "atlasIndex": 0, "textureRect": [16, 16, 8, 8]},
		{"id": 19, "name": "", "atlasIndex": 0, "textureRect": [24, 16, 8, 8]},
		{"id": 20, "name": "", "atlasIndex": 0, "textureRect": [32, 16, 8, 8]},
		{"id": 21, "name": "", "atlasIndex": 0, "textureRect": [40, 16, 8, 8]},
		{"id": 22, "name": "", "atlasIndex": 0, "textureRect": [48, 16, 8, 8]},
		{"id": 23, "name": "", "atlasIndex": 0, "textureRect": [56, 16, 8, 8]},
		{"id": 24, "name": "", "atlasIndex": 0, "textureRect": [0, 24, 8, 8]},
		{"id": 25, "name": "", "atlasIndex": 0, "textureRect": [8, 24, 8, 8]},
		{"id": 26, "name": "", "atlasIndex": 0, "textureRect": [16, 24, 8, 8]},
		{"id": 27, "name": "", "atlasIndex": 0, "textureRect": [24, 24, 8, 8]},
		{"id": 28, "name": "", "atlasIndex": 0, "textureRect": [32, 24, 8, 8]},
		{"id": 29, "name": "", "atlasIndex": 0, "textureRect": [40, 24, 8, 8]},
		{"id": 30, "name": "", "atlasIndex": 0, "textureRect": [48, 24, 8, 8]},
		{"id": 31, "name": "", "atlasIndex": 0, "textureRect": [56, 24, 8, 8]},
		{"id": 32, "name": "", "atlasIndex": 0, "textureRect": [0, 32, 8, 8]},
		{"id": 33, "name": "", "atlasIndex": 0, "textureRect": [8, 32, 8, 8]},
		{"id": 34, "name": "", "atlasIndex": 0, "textureRect": [16, 32, 8, 8]},
		{"id": 35, "name": "", "atlasIndex": 0, "textureRect": [24, 32, 8, 8]},
		{"id": 36, "name": "", "atlasIndex": 0, "textureRect": [32, 32, 8, 8]},
		{"id": 37, "name": "", "atlasIndex": 0, "textureRect": [40, 32, 8, 8]},
		{"id": 38, "name": "", "atlasIndex": 0, "textureRect": [48, 32, 8, 8]},
		{"id": 39, "name": "", "atlasIndex": 0, "textureRect": [56, 32, 8, 8]},
		{"id": 40, "name": "", "atlasIndex": 0, "textureRect": [0, 40, 8, 8]},
		{"id": 41, "name": "", "atlasIndex": 0, "textureRect": [8, 40, 8, 8]},
		{"id": 42, "name": "", "atlasIndex": 0, "textureRect": [16, 40, 8, 8]},
		{"id": 43, "name": "", "atlasIndex": 0, "textureRect": [24, 40, 8, 8]},
		{"id": 44, "name": "", "atlasIndex": 0, "textureRect": [32, 40, 8, 8]},
		{"id": 45, "name": "", "atlasIndex": 0, "textureRect": [40, 40, 8, 8]},
		{"id": 46, "name": "", "atlasIndex": 0, "textureRect": [48, 40, 8, 8]},
		{"id": 47, "name": "", "atlasIndex": 0, "textureRect": [56, 40, 8, 8]},
		{"id": 48, "name": "", "atlasIndex": 0, "textureRect": [0, 48, 8, 8]},
		{"id": 49, "name": "", "atlasIndex": 0, "textureRect": [8, 48, 8, 8]},
		{"id": 50, "name": "", "atlasIndex": 0, "textureRect": [16, 48, 8, 8]},
		{"id": 51, "name": "", "atlasIndex": 0, "textureRect": [24, 48, 8, 8]},
		{"id": 52, "name": "", "atlasIndex": 0, "textureRect": [32, 48, 8, 8]},
		{"id": 53, "name": "", "atlasIndex": 0, "textureRect": [40, 48, 8, 8]},
		{"id": 54, "name": "", "atlasIndex": 0, "textureRect": [48, 48, 8, 8]},
		{"id": 55, "name": "", "atlasIndex": 0, "textureRect": [56, 48, 8, 8]},
		{"id": 56, "name": "", "atlasIndex": 0, "textureRect": [0, 56, 8, 8]},
		{"id": 57, "name": "", "atlasIndex": 0, "textureRect": [8, 56, 8, 8]},
		{"id": 58, "name": "", "atlasIndex": 0, "textureRect": [16, 56, 8, 8]},
		{"id": 59, "name": "", "atlasIndex": 0, "textureRect": [24, 56, 8, 8]},
		{"id": 60, "name": "", "atlasIndex": 0, "textureRect": [32, 56, 8, 8]},
		{"id": 61, "name": "", "atlasIndex": 0, "textureRect": [40, 56, 8, 8]},
		{"id": 62, "name": "", "atlasIndex": 0, "textureRect": [48, 56, 8, 8]},
		{"id": 63, "name": "", "atlasIndex": 0, "textureRect": [56, 56, 8, 8]},
		{"id": 64, "name": "", "atlasIndex": 0, "textureRect": [0, 64, 8, 8]},
		{"id": 65, "name": "", "atlasIndex": 0, "textureRect": [8, 64, 8, 8]},
		{"id": 66, "name": "", "atlasIndex": 0, "textureRect": [16, 64, 8, 8]},
		{"id": 67, "name": "", "atlasIndex": 0, "textureRect": [24, 64, 8, 8]},
		{"id": 68, "name": "", "atlasIndex": 0, "textureRect": [32, 64, 8, 8]},
		{"id": 69, "name": "", "atlasIndex": 0, "textureRect": [40, 64, 8, 8]},
		{"id": 70, "name": "", "atlasIndex": 0, "textureRect": [48, 64, 8, 8]},
		{"id": 71, "name": "", "atlasIndex": 0, "textureRect": [56, 64, 8, 8]},
		{"id": 72, "name": "", "atlasIndex": 0, "textureRect": [0, 72, 8, 8]},
		{"id": 73, "name": "", "atlasIndex": 0, "textureRect": [8, 72, 8, 8]},
		{"id": 74, "name": "", "atlasIndex": 0, "textureRect": [16, 72, 8, 8]},
		{"id": 75, "name": "", "atlasIndex": 0, "textureRect": [24, 72, 8, 8]},
		{"id": 76, "name": "", "atlasIndex": 0, "textureRect": [32, 72, 8, 8]},
		{"id": 77, "name": "", "atlasIndex": 0, "textureRect": [40, 72, 8, 8]},
		{"id": 78, "name": "", "atlasIndex": 0, "textureRect": [48, 72, 8, 8]},
		{"id": 79, "name": "", "atlasIndex": 0, "textureRect": [56, 72, 8, 8]},
		{"id": 80, "name": "", "atlasIndex": 0, "textureRect": [0, 80, 8, 8]},
		{"id": 81, "name": "", "atlasIndex": 0, "textureRect": [8, 80, 8, 8]},
		{"id": 82, "name": "", "atlasIndex": 0, "textureRect": [16, 80, 8, 8]},
		{"id": 83, "name": "", "atlasIndex": 0, "textureRect": [24, 80, 8, 8]},
		{"id": 84, "name": "", "atlasIndex": 0, "textureRect": [32, 80, 8, 8]},
		{"id": 85, "name": "", "atlasIndex": 0, "textureRect": [40, 80, 8, 8]},
		{"id": 86, "name": "", "atlasIndex": 0, "textureRect": [48, 80, 8, 8]},
		{"id": 87, "name": "", "atlasIndex": 0, "textureRect": [56, 80, 8, 8]},
		{"id": 88, "name": "", "atlasIndex": 0, "textureRect": [0, 88, 8, 8]},
		{"id": 89, "name": "", "atlasIndex": 0, "textureRect": [8, 88, 8, 8]},
		{"id": 90, "name": "", "atlasIndex": 0, "textureRect": [16, 88, 8, 8]},
		{"id": 91, "name": "", "atlasIndex": 0, "textureRect": [24, 88, 8, 8]},
		{"id": 92, "name": "", "atlasIndex": 0, "textureRect": [32, 88, 8, 8]},
		{"id": 93, "name": "", "atlasIndex": 0, "textureRect": [40, 88, 8, 8]},
		{"id": 94, "name": "", "atlasIndex": 0, "textureRect": [48, 88, 8, 8]},
		{"id": 95, "name": "", "atlasIndex": 0, "textureRect": [56, 88, 8, 8]}
	]
}
